setup.py
algorithm/__init__.py
algorithm/ner/__init__.py
algorithm/ner/ner_search.py
algorithm/segmation/__init__.py
algorithm/segmation/backward_segment.py
algorithm/segmation/forward_segment.py
algorithm/segmation/longest_segment.py
algorithm/segmation/sentence_segment.py
algorithm/sentiment/__init__.py
algorithm/sentiment/dic_sentiment.py
data_process/__init__.py
data_process/remove_stopwords.py
data_structure/TrieTree.py
data_structure/__init__.py
dictionary/__init__.py
dictionary/dictionary_loader.py
qcnlp.egg-info/PKG-INFO
qcnlp.egg-info/SOURCES.txt
qcnlp.egg-info/dependency_links.txt
qcnlp.egg-info/top_level.txt